pycocos/__init__.py
pycocos/main.py
pycocos/components/__init__.py
pycocos/components/client.py
pycocos/components/enums.py
pycocos/components/exceptions.py
pycocos/components/urls.py
pyCocos-0.2.12.dist-info/LICENSE
pyCocos-0.2.12.dist-info/METADATA
pyCocos-0.2.12.dist-info/WHEEL
pyCocos-0.2.12.dist-info/top_level.txt
pyCocos-0.2.12.dist-info/RECORD
