Metadata-Version: 2.1
Name: pyCocos
Version: 0.2.12
Summary: Python connector for Cocos Capital's Rest APIs.
Home-page: https://github.com/nacho-herrera/pyCocos
Author: Nacho Herrera
Author-email: github@nachoherrera.com.ar
Classifier: Programming Language :: Python :: 3
Classifier: License :: OSI Approved :: MIT License
Classifier: Operating System :: OS Independent
Classifier: Development Status :: 4 - Beta
Classifier: Intended Audience :: Developers
Classifier: Intended Audience :: Information Technology
Classifier: Intended Audience :: Science/Research
Classifier: Topic :: Office/Business :: Financial :: Investment
Classifier: Topic :: Software Development
License-File: LICENSE
Requires-Dist: requests >=2.31.0
Requires-Dist: simplejson >=3.19.1
Requires-Dist: pyotp >=2.9.0
Requires-Dist: cloudscraper >=1.2.71
